CHANGES.txt
README.txt
setup.py
enfold/__init__.py
enfold.recipe.patch.egg-info/PKG-INFO
enfold.recipe.patch.egg-info/SOURCES.txt
enfold.recipe.patch.egg-info/dependency_links.txt
enfold.recipe.patch.egg-info/entry_points.txt
enfold.recipe.patch.egg-info/namespace_packages.txt
enfold.recipe.patch.egg-info/not-zip-safe
enfold.recipe.patch.egg-info/requires.txt
enfold.recipe.patch.egg-info/top_level.txt
enfold/recipe/__init__.py
enfold/recipe/patch/README.txt
enfold/recipe/patch/__init__.py