Metadata-Version: 1.0
Name: enfold.recipe.patch
Version: 1.0.2
Summary: zc.buildout recipe for applying patches to a buildout tree.
Home-page: http://cheeseshop.python.org/pypi/enfold.recipe.patch
Author: Sidnei da Silva
Author-email: sidnei@enfoldsystems.com
License: GPL
Keywords: development buildout recipe
Platform: UNKNOWN
Classifier: Framework :: Buildout
Classifier: Intended Audience :: Developers
Classifier: License :: OSI Approved :: GNU General Public License (GPL)
Classifier: Topic :: Software Development :: Build Tools
Classifier: Topic :: Software Development :: Libraries :: Python Modules
